demo_buzzjomy/__init__.py
demo_buzzjomy-0.1.0.dist-info/METADATA
demo_buzzjomy-0.1.0.dist-info/WHEEL
demo_buzzjomy-0.1.0.dist-info/RECORD
